pybamm_diffsol-0.0.1.dist-info/METADATA
pybamm_diffsol-0.0.1.dist-info/WHEEL
pybamm_diffsol-0.0.1.dist-info/licenses/LICENSE.txt
pybamm_diffsol/__init__.py
pybamm_diffsol/pybamm2diffsl.py
pybamm_diffsol/pybamm_diffsol.cpython-311-darwin.so
pybamm_diffsol-0.0.1.dist-info/RECORD
