Metadata-Version: 2.4
Name: pybamm_diffsol
Version: 0.0.1
Classifier: Programming Language :: Rust
Classifier: Programming Language :: Python :: Implementation :: CPython
Classifier: Programming Language :: Python :: Implementation :: PyPy
Requires-Dist: pybamm
Requires-Dist: numpy
Requires-Dist: scipy
Requires-Dist: pytest ; extra == 'dev'
Provides-Extra: dev
License-File: LICENSE.txt
Requires-Python: >=3.8
